fetchfinancialsexcel/__init__.py
fetchfinancialsexcel/cli.py
fetchfinancialsexcel/company_data_extraction_EODH.py
fetchfinancialsexcel/core.py
fetchfinancialsexcel/data_analysis.py
fetchfinancialsexcel-0.4.0.dist-info/licenses/LICENSE
fetchfinancialsexcel-0.4.0.dist-info/METADATA
fetchfinancialsexcel-0.4.0.dist-info/WHEEL
fetchfinancialsexcel-0.4.0.dist-info/entry_points.txt
fetchfinancialsexcel-0.4.0.dist-info/top_level.txt
fetchfinancialsexcel-0.4.0.dist-info/RECORD
