Metadata-Version: 2.4
Name: FetchFinancialsExcel
Version: 0.4.0
Summary: A Python package for fetching financial data from Excel files and performing fundamental analysis
Home-page: https://github.com/username/FetchFinancialsExcel
Author: Carl Viggo Gravenhorst-Lövenstierne
Author-email: 
Maintainer: Carl Viggo Gravenhorst-Lövenstierne
License: MIT
Project-URL: Homepage, https://github.com/username/FetchFinancialsExcel
Project-URL: Bug Reports, https://github.com/username/FetchFinancialsExcel/issues
Project-URL: Source Code, https://github.com/username/FetchFinancialsExcel
Project-URL: Documentation, https://github.com/username/FetchFinancialsExcel/blob/main/README.md
Keywords: finance,stocks,fundamental analysis,financial data,EODHD,excel
Classifier: Development Status :: 4 - Beta
Classifier: Intended Audience :: Financial and Insurance Industry
Classifier: Intended Audience :: Developers
Classifier: Topic :: Office/Business :: Financial :: Investment
Classifier: License :: OSI Approved :: MIT License
Classifier: Programming Language :: Python :: 3
Classifier: Programming Language :: Python :: 3.8
Classifier: Programming Language :: Python :: 3.9
Classifier: Programming Language :: Python :: 3.10
Classifier: Programming Language :: Python :: 3.11
Classifier: Programming Language :: Python :: 3.12
Requires-Python: >=3.8
License-File: LICENSE
Requires-Dist: requests>=2.25.0
Requires-Dist: pandas>=1.3.0
Requires-Dist: openpyxl>=3.0.0
Requires-Dist: numpy>=1.20.0
Requires-Dist: statsmodels>=0.13.0
Requires-Dist: scikit-learn>=1.0.0
Requires-Dist: pandas-datareader>=0.10.0
Dynamic: home-page
Dynamic: license-file
Dynamic: requires-python
